AUTHORS
CHANGELOG
COPYING
FAQ
INSTALL
MANIFEST.in
NEWS
README
THANKS
TODO
setup.cfg
setup.py
armsim/__init__.py
armsim/bitset.py
armsim/exceptions.py
armsim/simulator.py
armsim/utils.py
armsim.egg-info/PKG-INFO
armsim.egg-info/SOURCES.txt
armsim.egg-info/dependency_links.txt
armsim.egg-info/entry_points.txt
armsim.egg-info/not-zip-safe
armsim.egg-info/requires.txt
armsim.egg-info/top_level.txt
armsim/instruction/__init__.py
armsim/instruction/branch.py
armsim/instruction/dp.py
armsim/instruction/exception.py
armsim/instruction/ldstr.py
armsim/instruction/miscellaneous.py
armsim/instruction/mult.py
armsim/instruction/semaphore.py
armsim/instruction/status.py
armsim/interfaces/__init__.py
armsim/interfaces/arminstruction.py
armsim/interfaces/armprocessor.py
armsim/processor/__init__.py
armsim/processor/arm9processor.py
doc/docs/html/.buildinfo
doc/docs/html/armsim.zip
doc/docs/html/cosa
doc/docs/html/genindex.html
doc/docs/html/index.html
doc/docs/html/objects.inv
doc/docs/html/resources.html
doc/docs/html/search.html
doc/docs/html/searchindex.js
src/uartmodule.c