Metadata-Version: 1.0
Name: armsim
Version: 0.1development
Summary: ARM Simulator for Linux
Home-page: http://packages.python.org/armsim
Author: Eduardo Diaz
Author-email: iamedu@gmail.com
License: GPL
Platform: Linux
Classifier: Development Status :: 1 - Planning
Classifier: Operating System :: POSIX :: Linux
Classifier: Programming Language :: Python :: 2.6
Classifier: Programming Language :: C
Classifier: Topic :: Software Development :: Embedded Systems
Classifier: Topic :: System :: Emulators
